{
  "schemaVersion": 1,
  "id": "clean-debug",
  "version": "${version}",
  "name": "Clean F3",
  "description": "Removes useless information from the debug screen.",
  "authors": [
    "tyrannus"
  ],
  "contact": {
    "sources": "https://github.com/tyrannus00/CleanF3",
    "issues": "https://github.com/tyrannus00/CleanF3/issues"
  },
  "license": "MIT",
  "icon": "assets/clean-debug/icon.png",
  "environment": "client",
  "entrypoints": {
    "client": [
      "de.tyrannus.cleandebug.CleanDebug"
    ]
  },
  "mixins": [
    "clean-debug.mixins.json"
  ],
  "depends": {
    "minecraft": ">=1.20 <1.21.9",
    "midnightlib": "*",
    "java": ">=17"
  },
  "breaks": {
    "betterf3": "*"
  }
}